MANIFEST.in
setup.py
etc/pgup.yaml
pgup/__init__.py
pgup/build_diff.py
pgup/build_init.py
pgup/config.py
pgup/counter.py
pgup/diff_maker.py
pgup/errors.py
pgup/main.py
pgup/procedure.py
pgup/table.py
pgup.egg-info/PKG-INFO
pgup.egg-info/SOURCES.txt
pgup.egg-info/dependency_links.txt
pgup.egg-info/requires.txt
pgup.egg-info/top_level.txt
pgup/templates/alter_table.j2
pgup/templates/create_table.j2