Metadata-Version: 1.0
Name: pgup
Version: 0.5.1
Summary: pgup - util for build postgresql structure
Home-page: http://pythonhosted.org/pgup
Author: Stepan Perlov
Author-email: stepanperlov@gmail.com
License: MIT
Platform: linux
